flysystem/__init__.py
flysystem/error.py
flysystem/filesystem.py
flysystem/path.py
flysystem/visibility.py
flysystem/adapters/__init__.py
flysystem/adapters/ftp.py
flysystem/adapters/local.py
flysystem/adapters/memory.py
flysystem/adapters/s3.py
flysystem/adapters/sftp.py
flysystem/adapters/webdav.py
flysystem-0.1.1.dist-info/LICENSE.txt
flysystem-0.1.1.dist-info/METADATA
flysystem-0.1.1.dist-info/WHEEL
flysystem-0.1.1.dist-info/top_level.txt
flysystem-0.1.1.dist-info/RECORD
