Metadata-Version: 2.1
Name: flysystem
Version: 0.1.1
Summary: Abstraction for local and remote filesystems
Author-email: Oanh Nguyen <oanhnn.bk@gmail.com>
Maintainer-email: Rabiloo Developers <oss@rabiloo.com>
License: The MIT License
Project-URL: Homepage, https://github.com/rabiloo/python-flysystem
Project-URL: Repository, https://github.com/rabiloo/python-flysystem
Project-URL: Bug Tracker, https://github.com/rabiloo/python-flysystem/issues
Keywords: filesystem,storage,fs,s3,cloud-storage
Classifier: Programming Language :: Python :: 3
Classifier: License :: OSI Approved :: MIT License
Classifier: Operating System :: OS Independent
Classifier: Development Status :: 2 - Pre-Alpha
Requires-Python: >=3.10
License-File: LICENSE.txt
Requires-Dist: boto3
Provides-Extra: dev
Requires-Dist: black ; extra == 'dev'
Requires-Dist: flake8 ; extra == 'dev'
Requires-Dist: flake8-pyproject ; extra == 'dev'
Requires-Dist: pytest ; extra == 'dev'
Requires-Dist: typing-extensions ; extra == 'dev'
